{
  "frames": [
    {
      "filename": "walk-0",
      "frame": {
        "w": 320,
        "h": 320,
        "x": 0,
        "y": 0
      },
      "anchor": {
        "x": 0,
        "y": 0
      }
    },
    {
      "filename": "walk-1",
      "frame": {
        "w": 320,
        "h": 320,
        "x": 320,
        "y": 0
      },
      "anchor": {
        "x": 0,
        "y": 0
      }
    },
    {
      "filename": "walk-2",
      "frame": {
        "w": 320,
        "h": 320,
        "x": 640,
        "y": 0
      },
      "anchor": {
        "x": 0,
        "y": 0
      }
    },
    {
      "filename": "walk-3",
      "frame": {
        "w": 320,
        "h": 320,
        "x": 960,
        "y": 0
      },
      "anchor": {
        "x": 0,
        "y": 0
      }
    },
    {
      "filename": "walk-4",
      "frame": {
        "w": 320,
        "h": 320,
        "x": 0,
        "y": 320
      },
      "anchor": {
        "x": 0,
        "y": 0
      }
    },
    {
      "filename": "walk-5",
      "frame": {
        "w": 320,
        "h": 320,
        "x": 320,
        "y": 320
      },
      "anchor": {
        "x": 0,
        "y": 0
      }
    },
    {
      "filename": "walk-6",
      "frame": {
        "w": 320,
        "h": 320,
        "x": 640,
        "y": 320
      },
      "anchor": {
        "x": 0,
        "y": 0
      }
    },
    {
      "filename": "walk-7",
      "frame": {
        "w": 320,
        "h": 320,
        "x": 960,
        "y": 320
      },
      "anchor": {
        "x": 0,
        "y": 0
      }
    }
  ]
}
